mozilla_aws_cli/__init__.py
mozilla_aws_cli/cache.py
mozilla_aws_cli/cli.py
mozilla_aws_cli/config.py
mozilla_aws_cli/listener.py
mozilla_aws_cli/login.py
mozilla_aws_cli/role_picker.py
mozilla_aws_cli/sts_conn.py
mozilla_aws_cli/utils.py
mozilla_aws_cli/static/index.css
mozilla_aws_cli/static/index.html
mozilla_aws_cli/static/index.js
mozilla_aws_cli/static/fonts/open-sans-v17-latin_latin-ext-700.woff
mozilla_aws_cli/static/fonts/open-sans-v17-latin_latin-ext-700.woff2
mozilla_aws_cli/static/fonts/open-sans-v17-latin_latin-ext-regular.woff
mozilla_aws_cli/static/fonts/open-sans-v17-latin_latin-ext-regular.woff2
mozilla_aws_cli/static/fonts/zilla-slab-v4-latin_latin-ext-700.woff
mozilla_aws_cli/static/fonts/zilla-slab-v4-latin_latin-ext-700.woff2
mozilla_aws_cli/static/fonts/zilla-slab-v4-latin_latin-ext-regular.woff
mozilla_aws_cli/static/fonts/zilla-slab-v4-latin_latin-ext-regular.woff2
mozilla_aws_cli/static/js/handlebars-v4.4.3.js
mozilla_aws_cli/static/js/jquery-3.4.1.min.js
mozilla_aws_cli-1.2.5.dist-info/LICENSE
mozilla_aws_cli-1.2.5.dist-info/METADATA
mozilla_aws_cli-1.2.5.dist-info/WHEEL
mozilla_aws_cli-1.2.5.dist-info/entry_points.txt
mozilla_aws_cli-1.2.5.dist-info/top_level.txt
mozilla_aws_cli-1.2.5.dist-info/RECORD
