Metadata-Version: 2.1
Name: mozilla-aws-cli
Version: 1.2.5
Summary: Command line tool to enable accessing AWS using federated single sign on
Home-page: https://github.com/mozilla-iam/mozilla-aws-cli
Author: Mozilla Enterprise Information Security
Author-email: iam@discourse.mozilla.org
License: UNKNOWN
Keywords: maws Mozilla AWS CLI
Platform: UNKNOWN
Classifier: Development Status :: 5 - Production/Stable
Classifier: Intended Audience :: Developers
Classifier: License :: OSI Approved :: Mozilla Public License 2.0 (MPL 2.0)
Classifier: Natural Language :: English
Classifier: Programming Language :: Python :: 2
Classifier: Programming Language :: Python :: 2.7
Classifier: Programming Language :: Python :: 3
Classifier: Programming Language :: Python :: 3.4
Classifier: Programming Language :: Python :: 3.5
Classifier: Programming Language :: Python :: 3.6
Classifier: Programming Language :: Python :: 3.7
Classifier: Programming Language :: Python :: 3.8
Classifier: Programming Language :: Python :: 3.9
License-File: LICENSE
Requires-Dist: appdirs
Requires-Dist: Click (>=6.0)
Requires-Dist: flask (>=1.0.2)
Requires-Dist: Werkzeug (<2.1.0)
Requires-Dist: future
Requires-Dist: requests (>=2.20.1)
Requires-Dist: whichcraft (==0.6.1)
Requires-Dist: python-jose (<3.3.0) ; python_version < "3.0"
Requires-Dist: rsa (==4.5) ; python_version < "3.0"
Requires-Dist: python-jose ; python_version >= "3.0"
Requires-Dist: rsa ; python_version >= "3.0"
Provides-Extra: test
Requires-Dist: pytest ; extra == 'test'
Requires-Dist: pytest-cov ; extra == 'test'
Requires-Dist: python-jose ; extra == 'test'
Requires-Dist: requests-mock ; extra == 'test'
Requires-Dist: mock ; (python_version < "3.3") and extra == 'test'
